rust_simulation_tools-0.1.7.dist-info/METADATA
rust_simulation_tools-0.1.7.dist-info/WHEEL
rust_simulation_tools/__init__.py
rust_simulation_tools/rust_simulation_tools.cpython-311-x86_64-linux-gnu.so
rust_simulation_tools-0.1.7.dist-info/RECORD
