Metadata-Version: 2.4
Name: rust_simulation_tools
Version: 0.1.7
Classifier: Programming Language :: Rust
Classifier: Programming Language :: Python :: Implementation :: CPython
Requires-Dist: numpy>=1.20
Summary: Fast algorithms for MD trajectories
Author-email: Matt Sinclair <msinclair@anl.gov>
Requires-Python: >=3.8
